setup.py
norm_dist_generator/Binomialdistribution.py
norm_dist_generator/Gaussiandistribution.py
norm_dist_generator/Generaldistribution.py
norm_dist_generator/__init__.py
normal_distributions.egg-info/PKG-INFO
normal_distributions.egg-info/SOURCES.txt
normal_distributions.egg-info/dependency_links.txt
normal_distributions.egg-info/not-zip-safe
normal_distributions.egg-info/top_level.txt