Metadata-Version: 1.0
Name: normal-distributions
Version: 0.2
Summary: normal distributions
Home-page: UNKNOWN
Author: UNKNOWN
Author-email: UNKNOWN
License: UNKNOWN
Platform: UNKNOWN
